CHANGELOG.txt
LICENCE.txt
MANIFEST.in
README.txt
setup.py
eam_ml.egg-info/PKG-INFO
eam_ml.egg-info/SOURCES.txt
eam_ml.egg-info/dependency_links.txt
eam_ml.egg-info/top_level.txt
mlpkg/SVM_algo.py
mlpkg/__init__.py
mlpkg/adaboost.py
mlpkg/cand-elim.py
mlpkg/finds-algo.py
mlpkg/id3-algo.py
mlpkg/ids-algo.py
mlpkg/k-means.py
mlpkg/linear-reg.py
mlpkg/logistic-reg.py
mlpkg/ml.py
mlpkg/mlp.py
mlpkg/random-forest.py
mlpkg/sl-perceptron.py
mlpkg/som.txt
mlpkg/stacking.py
mlpkg/xorper.py