Metadata-Version: 1.1
Name: eam-ml
Version: 0.0.3
Summary: A very basic calculator
Home-page: UNKNOWN
Author: EliteAppMakers
Author-email: eliteappmakers@gmail.com
License: MIT
Keywords: ml
Platform: UNKNOWN
Classifier: Development Status :: 5 - Production/Stable
Classifier: Intended Audience :: Education
Classifier: Operating System :: Microsoft :: Windows :: Windows 10
Classifier: License :: OSI Approved :: MIT License
Classifier: Programming Language :: Python :: 3
